odoo/addons/sale_quick_seasonality/README.rst
odoo/addons/sale_quick_seasonality/__init__.py
odoo/addons/sale_quick_seasonality/__manifest__.py
odoo/addons/sale_quick_seasonality/i18n/es.po
odoo/addons/sale_quick_seasonality/i18n/it.po
odoo/addons/sale_quick_seasonality/i18n/sale_quick_seasonality.pot
odoo/addons/sale_quick_seasonality/models/__init__.py
odoo/addons/sale_quick_seasonality/models/sale_order.py
odoo/addons/sale_quick_seasonality/readme/CONTRIBUTORS.rst
odoo/addons/sale_quick_seasonality/readme/DESCRIPTION.rst
odoo/addons/sale_quick_seasonality/static/description/icon.png
odoo/addons/sale_quick_seasonality/static/description/index.html
odoo/addons/sale_quick_seasonality/tests/__init__.py
odoo/addons/sale_quick_seasonality/tests/common.py
odoo/addons/sale_quick_seasonality/tests/test_sale_order.py
odoo14_addon_sale_quick_seasonality-14.0.1.0.1.dev7.dist-info/METADATA
odoo14_addon_sale_quick_seasonality-14.0.1.0.1.dev7.dist-info/WHEEL
odoo14_addon_sale_quick_seasonality-14.0.1.0.1.dev7.dist-info/top_level.txt
odoo14_addon_sale_quick_seasonality-14.0.1.0.1.dev7.dist-info/RECORD
